src/constants.py
src/constants_sandbox.py
src/docai.py
src/docai_processor_config.yaml
src/excel_processing.py
src/io.py
src/llm.py
src/log_setup.py
src/pdf_processing.py
src/postprocessing/common.py
src/postprocessing/postprocess_booking_confirmation.py
src/postprocessing/postprocess_commercial_invoice.py
src/postprocessing/postprocess_partner_invoice.py
src/prompts/library/arrivalNotice/other/placeholders.json
src/prompts/library/arrivalNotice/other/prompt.txt
src/prompts/library/bookingConfirmation/evergreen/placeholders.json
src/prompts/library/bookingConfirmation/evergreen/prompt.txt
src/prompts/library/bookingConfirmation/hapag-lloyd/placeholders.json
src/prompts/library/bookingConfirmation/hapag-lloyd/prompt.txt
src/prompts/library/bookingConfirmation/maersk/placeholders.json
src/prompts/library/bookingConfirmation/maersk/prompt.txt
src/prompts/library/bookingConfirmation/msc/placeholders.json
src/prompts/library/bookingConfirmation/msc/prompt.txt
src/prompts/library/bookingConfirmation/oocl/placeholders.json
src/prompts/library/bookingConfirmation/oocl/prompt.txt
src/prompts/library/bookingConfirmation/other/placeholders.json
src/prompts/library/bookingConfirmation/other/prompt.txt
src/prompts/library/bookingConfirmation/yangming/placeholders.json
src/prompts/library/bookingConfirmation/yangming/prompt.txt
src/prompts/library/bundeskasse/other/placeholders.json
src/prompts/library/bundeskasse/other/prompt.txt
src/prompts/library/commercialInvoice/other/placeholders.json
src/prompts/library/commercialInvoice/other/prompt.txt
src/prompts/library/customsAssessment/other/placeholders.json
src/prompts/library/customsAssessment/other/prompt.txt
src/prompts/library/customsInvoice/other/placeholders.json
src/prompts/library/customsInvoice/other/prompt.txt
src/prompts/library/deliveryOrder/other/placeholders.json
src/prompts/library/deliveryOrder/other/prompt.txt
src/prompts/library/draftMbl/other/placeholders.json
src/prompts/library/draftMbl/other/prompt.txt
data_science_document_ai-1.60.3.dist-info/METADATA
data_science_document_ai-1.60.3.dist-info/WHEEL
data_science_document_ai-1.60.3.dist-info/RECORD
