Metadata-Version: 2.4
Name: data-science-document-ai
Version: 1.60.3
Summary: "Document AI repo for data science"
Author: Naomi Nguyen
Author-email: naomi.nguyen@forto.com
Requires-Python: >=3.9,<3.12
Classifier: Programming Language :: Python :: 3
Classifier: Programming Language :: Python :: 3.9
Classifier: Programming Language :: Python :: 3.10
Classifier: Programming Language :: Python :: 3.11
Requires-Dist: apscheduler (>=3.10.4,<4.0.0)
Requires-Dist: db-dtypes (>=1.2.0,<2.0.0)
Requires-Dist: ddtrace (>=2.20.0,<3.0.0)
Requires-Dist: fastapi (>=0.109.2,<0.110.0)
Requires-Dist: fitz (>=0.0.1.dev2,<0.0.2)
Requires-Dist: fuzzywuzzy (>=0.18.0,<0.19.0)
Requires-Dist: google (>=3.0.0,<4.0.0)
Requires-Dist: google-api-python-client (>=2.89.0,<3.0.0)
Requires-Dist: google-auth-oauthlib (>=1.0.0,<2.0.0)
Requires-Dist: google-cloud-aiplatform (>=1.28.0,<2.0.0)
Requires-Dist: google-cloud-bigquery (>=3.11.3,<4.0.0)
Requires-Dist: google-cloud-bigquery-storage (>=2.20.0,<3.0.0)
Requires-Dist: google-cloud-documentai (>=2.23.0,<3.0.0)
Requires-Dist: google-cloud-storage (>=2.9.0,<3.0.0)
Requires-Dist: google-cloud-vision (>=3.7.1,<4.0.0)
Requires-Dist: gspread (>=6.1.0,<7.0.0)
Requires-Dist: httpx (>=0.26.0,<0.27.0)
Requires-Dist: jupyter (>=1.0.0,<2.0.0)
Requires-Dist: kubernetes (>=30.1.0,<31.0.0)
Requires-Dist: nltk (>=3.9.1,<4.0.0)
Requires-Dist: numpy (>=1.25.1,<2.0.0)
Requires-Dist: openai (>=1.53.0,<2.0.0)
Requires-Dist: openpyxl (>=3.1.5,<4.0.0)
Requires-Dist: pandas (>=2.0.3,<3.0.0)
Requires-Dist: parameterized (>=0.9.0,<0.10.0)
Requires-Dist: pdf2image (>=1.17.0,<2.0.0)
Requires-Dist: pgzip (>=0.3.5,<0.4.0)
Requires-Dist: pyarrow (==16.1.0)
Requires-Dist: pymupdf (>=1.23.26,<2.0.0)
Requires-Dist: pypdf (>=6.1.2,<7.0.0)
Requires-Dist: python-dotenv (>=1.0.0,<2.0.0)
Requires-Dist: python-multipart (>=0.0.7,<0.0.8)
Requires-Dist: rapidfuzz (>=3.12.2,<4.0.0)
Requires-Dist: requests-toolbelt (>=1.0.0,<2.0.0)
Requires-Dist: tabulate (>=0.9.0,<0.10.0)
Requires-Dist: toml (>=0.10.2,<0.11.0)
Requires-Dist: tqdm (>=4.66.1,<5.0.0)
Requires-Dist: uvicorn[standard] (>=0.27.0.post1,<0.28.0)
Requires-Dist: xlrd (>=2.0.1,<3.0.0)
